setup.py
src/fixtures2/__init__.py
src/fixtures2/case.py
src/fixtures2/datetime.py
src/fixtures2/fixutil.py
src/fixtures2/mox.py
src/fixtures2/patches.py
src/fixtures2/streams.py
src/fixtures2.egg-info/PKG-INFO
src/fixtures2.egg-info/SOURCES.txt
src/fixtures2.egg-info/dependency_links.txt
src/fixtures2.egg-info/requires.txt
src/fixtures2.egg-info/top_level.txt