Metadata-Version: 1.1
Name: fixtures2
Version: 0.1.8
Summary: Fixtures2 is an extension of the fixtures test framework.
Home-page: https://github.com/cooledcoffee/fixtures2
Author: Mengchen LEE
Author-email: UNKNOWN
License: UNKNOWN
Platform: UNKNOWN
Classifier: Development Status :: 4 - Beta
Classifier: Intended Audience :: Developers
Classifier: Operating System :: OS Independent
Classifier: Programming Language :: Python
Classifier: Programming Language :: Python :: 2
Classifier: Programming Language :: Python :: 3
Classifier: Topic :: Software Development :: Libraries
